brotlicffi/_brotlicffi.pypy310-pp73-x86-linux-gnu.so
brotlicffi/__init__.py
brotlicffi/_api.py
brotlicffi/_build.py
brotlicffi-1.1.0.0.dist-info/LICENSE
brotlicffi-1.1.0.0.dist-info/top_level.txt
brotlicffi-1.1.0.0.dist-info/WHEEL
brotlicffi-1.1.0.0.dist-info/METADATA
brotlicffi-1.1.0.0.dist-info/RECORD
