Metadata-Version: 2.1
Name: brotlicffi
Version: 1.1.0.0
Summary: Python CFFI bindings to the Brotli library
Home-page: https://github.com/python-hyper/brotlicffi
Author: Cory Benfield
Author-email: cory@lukasa.co.uk
License: MIT
Classifier: Programming Language :: Python :: Implementation :: CPython
Classifier: Programming Language :: Python :: Implementation :: PyPy
Classifier: Programming Language :: Python :: 3
Classifier: Programming Language :: Python :: 3.7
Classifier: Programming Language :: Python :: 3.8
Classifier: Programming Language :: Python :: 3.9
Classifier: Programming Language :: Python :: 3.10
Classifier: Programming Language :: Python :: 3.11
Classifier: Programming Language :: Python :: 3.12
Requires-Python: >=3.7
License-File: LICENSE
